pyrtools/__init__.py
pyrtools/version.py
pyrtools/pyramids/GaussianPyramid.py
pyrtools/pyramids/LaplacianPyramid.py
pyrtools/pyramids/SteerablePyramidFreq.py
pyrtools/pyramids/SteerablePyramidSpace.py
pyrtools/pyramids/WaveletPyramid.py
pyrtools/pyramids/__init__.py
pyrtools/pyramids/filters.py
pyrtools/pyramids/pyr_utils.py
pyrtools/pyramids/pyramid.py
pyrtools/pyramids/steer.py
pyrtools/pyramids/c/__init__.py
pyrtools/pyramids/c/convolve.c
pyrtools/pyramids/c/convolve.h
pyrtools/pyramids/c/edges.c
pyrtools/pyramids/c/internal_pointOp.c
pyrtools/pyramids/c/internal_pointOp.h
pyrtools/pyramids/c/meta.h
pyrtools/pyramids/c/py.c
pyrtools/pyramids/c/wrap.c
pyrtools/pyramids/c/wrapConv.cp38-win_amd64.pyd
pyrtools/pyramids/c/wrapper.py
pyrtools/tools/__init__.py
pyrtools/tools/compare_matpyrtools.py
pyrtools/tools/convolutions.py
pyrtools/tools/display.py
pyrtools/tools/image_stats.py
pyrtools/tools/synthetic_images.py
pyrtools/tools/utils.py
pyrtools-1.0.10.dist-info/LICENSE
pyrtools-1.0.10.dist-info/METADATA
pyrtools-1.0.10.dist-info/WHEEL
pyrtools-1.0.10.dist-info/top_level.txt
pyrtools-1.0.10.dist-info/RECORD
