Metadata-Version: 2.1
Name: pyrtools
Version: 1.0.10
Summary: Python tools for multi-scale image processing, including Laplacian pyramids, Wavelets, and Steerable Pyramids.
Author: Pyrtools authors
Project-URL: Homepage, https://github.com/LabForComputationalVision/pyrtools
Project-URL: Documentation, https://pyrtools.readthedocs.io/en/latest/
Project-URL: Download, https://zenodo.org/records/10403034
Keywords: image processing,visual information processing,computational models
Classifier: Development Status :: 4 - Beta
Classifier: Programming Language :: Python :: 3
Classifier: License :: OSI Approved :: MIT License
Classifier: Intended Audience :: Science/Research
Requires-Python: >=3.8
License-File: LICENSE
Requires-Dist: numpy>=1.1
Requires-Dist: scipy>=0.18
Requires-Dist: matplotlib>=1.5
Requires-Dist: tqdm>=4.29
Requires-Dist: requests>=2.21
Provides-Extra: docs
Requires-Dist: sphinx; extra == "docs"
Requires-Dist: numpydoc; extra == "docs"
Requires-Dist: ipython; extra == "docs"
Requires-Dist: nbsphinx; extra == "docs"
Requires-Dist: nbsphinx-link; extra == "docs"
Requires-Dist: sphinxcontrib-apidoc; extra == "docs"
Requires-Dist: sphinx-rtd-theme>=1.3.0rc1; extra == "docs"
